README.md
setup.py
ochs/__init__.py
ochs/blog.py
ochs/cli.py
ochs/logger.py
ochs/pages.py
ochs/settings.py
ochs/templates.py
ochs/variables.py
ochs/website.py
ochs.egg-info/PKG-INFO
ochs.egg-info/SOURCES.txt
ochs.egg-info/dependency_links.txt
ochs.egg-info/entry_points.txt
ochs.egg-info/requires.txt
ochs.egg-info/top_level.txt