Metadata-Version: 1.1
Name: ochs
Version: 0.2a0
Summary: Tool for building static blogs based on Markdown posts, YAML files and handwritten HTML templates.
Home-page: https://github.com/vsartor/ochs
Author: Victhor Sartório
Author-email: victhor@vsartor.com
License: MIT
Keywords: blog,website,generator,cli
Platform: UNKNOWN
Classifier: Development Status :: 3 - Alpha
Classifier: Environment :: Console
Classifier: Intended Audience :: Developers
Classifier: Programming Language :: Python :: 3
Classifier: Programming Language :: Python :: 3 :: Only
Classifier: Programming Language :: Python :: 3.8
Classifier: Topic :: Internet
Classifier: Typing :: Typed
